README.md
setup.cfg
setup.py
kerasjr/Model.py
kerasjr/__init__.py
kerasjr.egg-info/PKG-INFO
kerasjr.egg-info/SOURCES.txt
kerasjr.egg-info/dependency_links.txt
kerasjr.egg-info/requires.txt
kerasjr.egg-info/top_level.txt