Metadata-Version: 2.1
Name: kerasjr
Version: 0.1.5
Summary: A python package to create and train simple dense neural networks.
Home-page: https://github.com/OliverMathias/kerasjr
Author: Oliver Mathias
Author-email: mathias@chapman.edu
License: MIT
Download-URL: https://github.com/OliverMathias/kerasjr/archive/0.09.tar.gz
Keywords: Dense,model,machine learning,Deep Learning,prediction
Platform: UNKNOWN
Classifier: Development Status :: 3 - Alpha
Classifier: Intended Audience :: Developers
Classifier: Topic :: Software Development :: Build Tools
Classifier: License :: OSI Approved :: MIT License
Classifier: Programming Language :: Python :: 3
Classifier: Programming Language :: Python :: 3.4
Classifier: Programming Language :: Python :: 3.5
Classifier: Programming Language :: Python :: 3.7
